[
  {
    "id": "cabbce0d-a5c5-4590-984b-c6995c81744f",
    "name": "Unlimited 1-month Plan",
    "regularity": "month",
    "currency": "$",
    "full_price": 6999,
    "discounted_price": 3999,
    "plan_ui_discount_text": "Most Popular"
  },
  {
    "id": "dabbce0d-a5c5-4590-984b-c6995c817789",
    "name": "7-day Access",
    "regularity": "month",
    "currency": "$",
    "trial_period": 7,
    "full_trial_price": 1000, 
    "discounted_trial_price": 100, 
    "full_price": 2999,
    "plan_ui_discount_text": "Save 90%"
  },
  {
    "id": "aabbce0d-a5c5-4590-984b-c6995c817123",
    "name": "Unlimited Annual Plan",
    "regularity": "month",
    "currency": "$",
    "full_price": 4900,
    "discounted_price": 2499,
    "plan_ui_discount_text": "Save 50%"
  }
] 